pysqlitecipher/__init__.py
pysqlitecipher/sqlitewrapper.py
pysqlitecipher-0.22.dist-info/LICENSE
pysqlitecipher-0.22.dist-info/LICENSE.txt
pysqlitecipher-0.22.dist-info/METADATA
pysqlitecipher-0.22.dist-info/WHEEL
pysqlitecipher-0.22.dist-info/top_level.txt
pysqlitecipher-0.22.dist-info/RECORD
