Metadata-Version: 2.1
Name: pysqlitecipher
Version: 0.22
Summary: Ligth weigth and easy to use sqlite wrapper with built in encryption system.
Home-page: https://github.com/harshnative/pysqlitecipher
Author: Harsh Native
Author-email: Harshnative@gmail.com
License: UNKNOWN
Platform: UNKNOWN
Classifier: Programming Language :: Python :: 3
Classifier: License :: OSI Approved :: MIT License
Classifier: Operating System :: OS Independent
Requires-Python: >=3.6
